humilis_kms
