Metadata-Version: 1.1
Name: humilis-kms
Version: 0.0.3
Summary: Humilis plug-in to deploy a Lambda humilis_kms
Home-page: https://github.com/humilis/humilis-kms
Author: German Gomez-Herrero, FindHotel BV
Author-email: german@findhotel.net
License: MIT
Platform: UNKNOWN
Classifier: Programming Language :: Python :: 3
